{ "compressionlevel":-1,
 "height":10,
 "infinite":false,
 "layers":[
        {
         "data":[11, 15, 12, 12, 12, 15, 15, 15, 15, 16,
            31, 32, 32, 32, 32, 32, 32, 32, 32, 96,
            31, 32, 32, 32, 32, 32, 32, 32, 32, 96,
            31, 32, 32, 32, 32, 32, 32, 32, 32, 96,
            31, 32, 32, 32, 32, 32, 32, 32, 32, 76,
            31, 32, 32, 32, 32, 32, 32, 32, 32, 76,
            31, 32, 32, 32, 32, 32, 32, 32, 32, 76,
            31, 32, 32, 32, 32, 32, 32, 32, 32, 76,
            31, 32, 32, 32, 32, 32, 32, 32, 32, 96,
            111, 112, 112, 112, 112, 112, 112, 112, 112, 116],
         "height":10,
         "id":1,
         "name":"Capa de patrones 1",
         "opacity":1,
         "type":"tilelayer",
         "visible":true,
         "width":10,
         "x":0,
         "y":0
        }, 
        {
         "data":[0, 0, 0, 0, 0, 0, 0, 0, 0, 0,
            0, 161, 162, 163, 164, 165, 166, 167, 168, 0,
            0, 169, 170, 171, 172, 173, 174, 175, 176, 0,
            0, 177, 178, 179, 180, 181, 182, 183, 184, 0,
            0, 185, 186, 187, 188, 189, 190, 191, 192, 0,
            0, 193, 194, 195, 196, 197, 198, 199, 200, 0,
            0, 201, 202, 203, 204, 205, 206, 207, 208, 0,
            0, 209, 210, 211, 212, 213, 214, 215, 216, 0,
            0, 217, 218, 219, 220, 221, 222, 223, 224, 0,
            0, 0, 0, 0, 0, 0, 0, 0, 0, 0],
         "height":10,
         "id":6,
         "name":"Capa de patrones 2",
         "opacity":1,
         "type":"tilelayer",
         "visible":true,
         "width":10,
         "x":0,
         "y":0
        }],
 "nextlayerid":9,
 "nextobjectid":1,
 "orientation":"orthogonal",
 "renderorder":"right-down",
 "tiledversion":"1.11.2",
 "tileheight":32,
 "tilesets":[
        {
         "firstgid":1,
         "source":"..\/..\/..\/..\/..\/Tilemap_Flat.tsx"
        }, 
        {
         "firstgid":161,
         "source":"..\/..\/..\/..\/..\/Tilemap_Elevation.tsx"
        }],
 "tilewidth":32,
 "type":"map",
 "version":"1.10",
 "width":10
}